pyc3dsample/__init__.py
pyc3dsample/pyc3dsample.py
pyc3dsample-0.0.4.dist-info/METADATA
pyc3dsample-0.0.4.dist-info/WHEEL
pyc3dsample-0.0.4.dist-info/entry_points.txt
pyc3dsample-0.0.4.dist-info/licenses/LICENSE
pyc3dsample-0.0.4.dist-info/RECORD
