Metadata-Version: 2.4
Name: pyc3dsample
Version: 0.0.4
Summary: Interface to easily deal with a C3D file, including some helpful methods for dealing with gait analysis (e.g. detecting heel strike)
License-File: LICENSE
Requires-Python: >=3.13
Requires-Dist: ezc3d<1.6
Requires-Dist: matplotlib>=3.10.8
Requires-Dist: numpy>=2.3.5
